atomic_mcp/__init__.py
atomic_mcp/cli/__init__.py
atomic_mcp/cli/main.py
atomic_mcp/client/__init__.py
atomic_mcp/server/__init__.py
atomic_mcp/server/interfaces/__init__.py
atomic_mcp/server/interfaces/middleware.py
atomic_mcp/server/interfaces/resource.py
atomic_mcp/server/interfaces/tool.py
atomic_mcp/server/middleware/__init__.py
atomic_mcp/server/middleware/logging.py
atomic_mcp/server/server.py
atomic_mcp/server/services/__init__.py
atomic_mcp/server/services/resource.py
atomic_mcp/server/services/tool.py
atomic_mcp-0.1.6.dist-info/LICENSE
atomic_mcp-0.1.6.dist-info/METADATA
atomic_mcp-0.1.6.dist-info/WHEEL
atomic_mcp-0.1.6.dist-info/entry_points.txt
atomic_mcp-0.1.6.dist-info/RECORD
