Metadata-Version: 2.3
Name: atomic-mcp
Version: 0.1.6
Summary: A framework for building MCP Servers using Atomic Agents and FastMCP
License: MIT
Author: jon fox
Author-email: jon@foxsolutions.dev
Requires-Python: <4.0,>=3.12
Classifier: License :: OSI Approved :: MIT License
Classifier: Programming Language :: Python :: 3
Classifier: Programming Language :: Python :: 3.12
Classifier: Programming Language :: Python :: 3.13
Requires-Dist: atomic-agents (>=2.0.1,<3.0.0)
Requires-Dist: fastmcp (>=2.11.0,<3.0.0)
